{"cameraMode":{"drawMode":0,"name":"Shaded","section":"Shading Mode"},"sceneLighting":true,"audioPlay":false,"sceneViewState":{"m_AlwaysRefresh":false,"showFog":true,"showSkybox":true,"showFlares":true,"showImageEffects":true,"showParticleSystems":true,"showVisualEffectGraphs":true,"m_FxEnabled":true},"in2DMode":false,"pivot":{"x":-6.73887825012207,"y":104.4911117553711,"z":-1.5733144283294678},"rotation":{"x":0.09712424129247666,"y":-0.28028741478919985,"z":0.02851942740380764,"w":0.9545683264732361},"size":1.3249871730804444,"orthographic":false}